{
  "gender": "female",
  "species": "octopus",
  "birthday": "6-26",
  "games": {
    "afe+": {
      "personality": "normal",
      "clothes": "red-aloha-shirt",
      "song": "Soulful K.K."
    },
    "ww": {
      "personality": "normal",
      "clothes": "bubble-gum-tee",
      "song": "Soulful K.K.",
      "phrase": "blurp",
      "quote": "I think I'm the only sane one in this town."
    },
    "cf": {
      "personality": "normal",
      "clothes": "bubble-gum-tee",
      "song": "Soulful K.K.",
      "phrase": "blurp"
    },
    "nl": {
      "personality": "normal",
      "clothes": "bubble-gum-tee",
      "song": "Soulful K.K.",
      "phrase": "blurp",
      "fear": "Skeleton Hood",
      "quote": "If you can't say something nice, don't say anything at all.",
      "skill": "Tongue twisters",
      "goal": "Pharmacist",
      "siblings": "Middle triplet",
      "favoriteStyle": "Official",
      "dislikedStyle": "Sporty",
      "favoriteColor": "pink",
      "coffee": {
        "beans": "Blue Mountain",
        "milk": "Lots of milk",
        "sugar": "Three spoonfuls of sugar"
      }
    },
    "nh": {
      "personality": "normal",
      "phrase": "blurp",
      "song": "Soulful K.K."
    }
  },
  "name": "Marina",
  "id": "marina"
}